cybertemp/__init__.py
cybertemp/client.py
cybertemp/http_client.py
cybertemp_wrapper_py-1.0.0.dist-info/licenses/LICENCE.md
cybertemp_wrapper_py-1.0.0.dist-info/METADATA
cybertemp_wrapper_py-1.0.0.dist-info/WHEEL
cybertemp_wrapper_py-1.0.0.dist-info/top_level.txt
cybertemp_wrapper_py-1.0.0.dist-info/RECORD
