Metadata-Version: 2.4
Name: cybertemp-wrapper-py
Version: 1.0.0
Summary: A Python wrapper for the CyberTemp email API.
Home-page: https://github.com/raz461/cybertemp-wrapper-py
Author: Never
License: MIT
Project-URL: Homepage, https://github.com/raz461/cybertemp-wrapper-py
Project-URL: BugTracker, https://github.com/raz461/cybertemp-wrapper-py/issues
Requires-Python: >=3.10
License-File: LICENCE.md
Requires-Dist: requests
Dynamic: home-page
Dynamic: license-file
Dynamic: requires-python
